cumulus_library_covid/__init__.py
cumulus_library_covid/builder_gpt.jinja
cumulus_library_covid/builder_gpt.py
cumulus_library_covid/counts.py
cumulus_library_covid/counts.sql
cumulus_library_covid/define_age_general.sql
cumulus_library_covid/define_age_pediatric.sql
cumulus_library_covid/define_dx_icd10.sql
cumulus_library_covid/define_dx_snomed.sql
cumulus_library_covid/define_ed_note.sql
cumulus_library_covid/define_pcr.sql
cumulus_library_covid/define_pcr_custom.sql
cumulus_library_covid/define_pcr_negative.sql
cumulus_library_covid/define_pcr_positive.sql
cumulus_library_covid/define_study_period.sql
cumulus_library_covid/define_symptom.py
cumulus_library_covid/define_symptom.sql
cumulus_library_covid/manifest.toml
cumulus_library_covid/table_dx.sql
cumulus_library_covid/table_pcr.sql
cumulus_library_covid/table_prevalence_ed.sql
cumulus_library_covid/table_study_period.sql
cumulus_library_covid/table_symptom.sql
cumulus_library_covid/valueset_dx_icd10.json
cumulus_library_covid/valueset_dx_snomed.json
cumulus_library_covid/valueset_pcr_interpretation.json
cumulus_library_covid/valueset_pcr_negative.json
cumulus_library_covid/valueset_pcr_positive.json
cumulus_library_covid/valueset_pcr_qualitative.json
cumulus_library_covid/valueset_pcr_qualitative_quantitative.json
cumulus_library_covid/version.sql
cumulus_library_covid-2.1.0.dist-info/WHEEL
cumulus_library_covid-2.1.0.dist-info/METADATA
cumulus_library_covid-2.1.0.dist-info/RECORD
