Metadata-Version: 2.1
Name: cumulus-library-covid
Version: 2.1.0
Summary: SQL generation for cumulus covid symptom analysis
Requires-Python: >= 3.11
Classifier: License :: OSI Approved :: Apache Software License
Classifier: Operating System :: OS Independent
Classifier: Programming Language :: Python :: 3
Classifier: Topic :: Software Development :: Libraries :: Python Modules
Requires-Dist: cumulus-library >= 3.0, <4
Requires-Dist: sqlfluff >= 3
Requires-Dist: ruff < 0.6 ; extra == "dev"
Requires-Dist: duckdb ; extra == "tests"
Requires-Dist: pandas ; extra == "tests"
Project-URL: Documentation, https://docs.smarthealthit.org/cumulus/
Project-URL: Home, https://smarthealthit.org/cumulus
Project-URL: Source, https://github.com/smart-on-fhir/cumulus-library-covid
Provides-Extra: dev
Provides-Extra: tests
